apkutils3/__init__.py
apkutils3/__main__.py
apkutils3/axml/arscparser.py
apkutils3/axml/axmlparser.py
apkutils3/axml/chunk.py
apkutils3/axml/public.py
apkutils3/cert.py
apkutils3/consts.py
apkutils3/custom_typing.py
apkutils3/dex/__init__.py
apkutils3/dex/byteio.py
apkutils3/dex/dalvik.py
apkutils3/dex/dalvikformats.py
apkutils3/dex/dexparser.py
apkutils3/dex/flags.py
apkutils3/dex/mutf8.py
apkutils3/dex/treelist.py
apkutils3/dex/util.py
apkutils3/elf/__init__.py
apkutils3/elf/elfparser.py
apkutils3/gui/__init__.py
apkutils3/gui/__main__.py
apkutils3/gui/android.ico
apkutils3/manifest.py
apkutils3-2.0.11.dist-info/LICENSE
apkutils3-2.0.11.dist-info/METADATA
apkutils3-2.0.11.dist-info/WHEEL
apkutils3-2.0.11.dist-info/RECORD
