Metadata-Version: 2.1
Name: apkutils3
Version: 2.0.11
Summary: Utils for parsing apk. Type hinting supported.
License: MIT
Author: LY
Author-email: ly-niko@qq.com
Requires-Python: >=3.11,<4.0
Classifier: Development Status :: 4 - Beta
Classifier: License :: OSI Approved :: MIT License
Classifier: Programming Language :: Python :: 3
Classifier: Programming Language :: Python :: 3.11
Classifier: Programming Language :: Python :: 3.12
Classifier: Programming Language :: Python :: 3 :: Only
Classifier: Topic :: Utilities
Provides-Extra: cert
Requires-Dist: cigam (>=0.0.3,<0.0.4)
Requires-Dist: pyelftools (>=0.30,<0.31)
Requires-Dist: xmltodict (>=0.13.0,<0.14.0)
